whitebox_plugin_demo_mode/__init__.py
whitebox_plugin_demo_mode/jsx/DemoModeServiceComponent.jsx
whitebox_plugin_demo_mode/whitebox_plugin_demo_mode.py
whitebox_test_plugin_demo_mode/__init__.py
whitebox_test_plugin_demo_mode/test_whitebox_plugin_demo_mode.py
whitebox_plugin_demo_mode-0.1.1.dist-info/LICENSE
whitebox_plugin_demo_mode-0.1.1.dist-info/METADATA
whitebox_plugin_demo_mode-0.1.1.dist-info/WHEEL
whitebox_plugin_demo_mode-0.1.1.dist-info/RECORD
